dalle3_gen_save.py
dalle3_gen_save-4.5.55.dist-info/METADATA
dalle3_gen_save-4.5.55.dist-info/WHEEL
dalle3_gen_save-4.5.55.dist-info/entry_points.txt
dalle3_gen_save-4.5.55.dist-info/RECORD
