Metadata-Version: 2.3
Name: dalle3_gen_save
Version: 4.5.55
Requires-Dist: openai
Requires-Dist: python-dotenv
